dask_jobqueue/__init__.py
dask_jobqueue/_version.py
dask_jobqueue/config.py
dask_jobqueue/core.py
dask_jobqueue/htcondor.py
dask_jobqueue/jobqueue.yaml
dask_jobqueue/local.py
dask_jobqueue/lsf.py
dask_jobqueue/moab.py
dask_jobqueue/oar.py
dask_jobqueue/pbs.py
dask_jobqueue/py.typed
dask_jobqueue/runner.py
dask_jobqueue/sge.py
dask_jobqueue/slurm.py
dask_jobqueue/tests/__init__.py
dask_jobqueue/tests/test_htcondor.py
dask_jobqueue/tests/test_job.py
dask_jobqueue/tests/test_jobqueue_core.py
dask_jobqueue/tests/test_lsf.py
dask_jobqueue/tests/test_oar.py
dask_jobqueue/tests/test_pbs.py
dask_jobqueue/tests/test_runner.py
dask_jobqueue/tests/test_sge.py
dask_jobqueue/tests/test_slurm.py
dask_jobqueue/tests/slurm_runner/basic.py
dask_jobqueue-0.9.0.dist-info/LICENSE.txt
dask_jobqueue-0.9.0.dist-info/METADATA
dask_jobqueue-0.9.0.dist-info/WHEEL
dask_jobqueue-0.9.0.dist-info/top_level.txt
dask_jobqueue-0.9.0.dist-info/RECORD
