Metadata-Version: 2.1
Name: dask-jobqueue
Version: 0.9.0
Summary: Deploy Dask on job queuing systems like PBS, Slurm, SGE or LSF
Home-page: https://jobqueue.dask.org
License: BSD 3-Clause
Requires-Python: >=3.10
License-File: LICENSE.txt
Requires-Dist: dask>=2022.02.0
Requires-Dist: distributed>=2022.02.0
Provides-Extra: test
Requires-Dist: pytest; extra == "test"
Requires-Dist: pytest-asyncio; extra == "test"
Requires-Dist: cryptography; extra == "test"
